checkout-psp-client/__init__.py
checkout2/__init__.py
checkout2/api.py
checkout_psp_client-0.0.1.dist-info/LICENSE
checkout_psp_client-0.0.1.dist-info/METADATA
checkout_psp_client-0.0.1.dist-info/WHEEL
checkout_psp_client-0.0.1.dist-info/top_level.txt
checkout_psp_client-0.0.1.dist-info/RECORD
