Metadata-Version: 2.1
Name: checkout-psp-client
Version: 0.0.1
Summary: Wrapper for the Checkout Finland Payment Service API
Home-page: https://github.com/ajkaijanaho/checkout-psp-client
Author: Antti-Juhani Kaijanaho
Author-email: antti-juhani@kaijanaho.fi
License: UNKNOWN
Platform: UNKNOWN
Classifier: Development Status :: 3 - Alpha
Classifier: Environment :: Web Environment
Classifier: Intended Audience :: Developers
Classifier: License :: OSI Approved :: MIT License
Classifier: Programming Language :: Python :: 3
Classifier: Programming Language :: Python :: 3.7
Classifier: Topic :: Office/Business
Requires-Python: >=3
Requires-Dist: requests
